<?xml version="1.0" encoding="UTF-8"?><record_update>
    <sys_choice action="DELETE" field="u_request_type" table="x_58872_needit_needit" version="3">
        <sys_choice_set action="DELETE">
            <element>u_request_type</element>
            <name>x_58872_needit_needit</name>
            <sys_class_name/>
            <sys_created_by/>
            <sys_created_on/>
            <sys_id/>
            <sys_mod_count/>
            <sys_name/>
            <sys_package/>
            <sys_policy/>
            <sys_scope/>
            <sys_update_name/>
            <sys_updated_by/>
            <sys_updated_on>2019-08-19 18:11:42</sys_updated_on>
        </sys_choice_set>
    </sys_choice>
    <sys_update_version action="INSERT_OR_UPDATE">
        <action>DELETE</action>
        <application/>
        <file_path/>
        <instance_id>eaef81bbdbdc734052cec59705961920</instance_id>
        <instance_name>dev77306</instance_name>
        <name>sys_choice_x_58872_needit_needit_u_request_type</name>
        <payload><![CDATA[<?xml version="1.0" encoding="UTF-8"?><record_update><sys_choice action="DELETE" field="u_request_type" table="x_58872_needit_needit" version="3"><sys_choice_set action="DELETE"><element>u_request_type</element><name>x_58872_needit_needit</name><sys_class_name/><sys_created_by/><sys_created_on/><sys_id/><sys_mod_count/><sys_name/><sys_package/><sys_policy/><sys_scope/><sys_update_name/><sys_updated_by/><sys_updated_on>2019-08-19 18:11:42</sys_updated_on></sys_choice_set></sys_choice></record_update>]]></payload>
        <payload_hash>1828161538</payload_hash>
        <record_name>x_58872_needit_needit.u_request_type</record_name>
        <reverted_from/>
        <source>1fbfa3aadb5333009cc5e9c9489619d6</source>
        <source_table>sys_update_set</source_table>
        <state>previous</state>
        <sys_created_by>admin</sys_created_by>
        <sys_created_on>2019-08-19 18:11:42</sys_created_on>
        <sys_id>670d84f6dbd333009cc5e9c94896199c</sys_id>
        <sys_mod_count>0</sys_mod_count>
        <sys_recorded_at>16cab13e13c0000001</sys_recorded_at>
        <sys_updated_by>admin</sys_updated_by>
        <sys_updated_on>2019-08-19 18:11:42</sys_updated_on>
        <type>Choice list</type>
        <update_guid>ef0d84f6c4d333002600afe0ecd6bd9b</update_guid>
        <update_guid_history>ef0d84f6c4d333002600afe0ecd6bd9b:1828161538,ab0d84f63dd33300a350793b00c1ac98:-103233526,2b0d84f6e0d33300f60ff64d0cc7d595:-854501905,a70d84f6ffd33300c1769463ffb54192:878753447,c111007ed493330008dcddd3be893064:411213506</update_guid_history>
    </sys_update_version>
    <sys_metadata_delete action="INSERT_OR_UPDATE">
        <sys_audit_delete/>
        <sys_class_name>sys_metadata_delete</sys_class_name>
        <sys_created_by>admin</sys_created_by>
        <sys_created_on>2019-08-19 18:11:49</sys_created_on>
        <sys_db_object display_value="" name="sys_choice_set">sys_choice_set</sys_db_object>
        <sys_id>491d08f6dbd333009cc5e9c948961939</sys_id>
        <sys_metadata>491d08f6dbd333009cc5e9c948961939</sys_metadata>
        <sys_mod_count>0</sys_mod_count>
        <sys_name>u_request_type</sys_name>
        <sys_package display_value="NeedIt" source="x_58872_needit">6ead8e780f603200cd674f8ce1050ed1</sys_package>
        <sys_parent/>
        <sys_policy/>
        <sys_scope display_value="NeedIt">6ead8e780f603200cd674f8ce1050ed1</sys_scope>
        <sys_scope_delete display_value="">94872a8897db403e8ee69a431de2fca4</sys_scope_delete>
        <sys_update_name>sys_choice_x_58872_needit_needit_u_request_type</sys_update_name>
        <sys_update_version display_value="sys_choice_x_58872_needit_needit_u_request_type">670d84f6dbd333009cc5e9c94896199c</sys_update_version>
        <sys_updated_by>admin</sys_updated_by>
        <sys_updated_on>2019-08-19 18:11:49</sys_updated_on>
    </sys_metadata_delete>
</record_update>
